auto_type_annotate.py
auto_type_annotate-1.1.1.dist-info/licenses/LICENSE
auto_type_annotate-1.1.1.dist-info/METADATA
auto_type_annotate-1.1.1.dist-info/WHEEL
auto_type_annotate-1.1.1.dist-info/entry_points.txt
auto_type_annotate-1.1.1.dist-info/top_level.txt
auto_type_annotate-1.1.1.dist-info/RECORD
