Metadata-Version: 2.4
Name: auto_type_annotate
Version: 1.1.1
Summary: automatically add annotations to untyped python code!
Home-page: https://github.com/getsentry/auto-type-annotate
Author: Sentry
Author-email: oss@sentry.io
License: Apache-2.0
Classifier: Programming Language :: Python :: 3
Classifier: Programming Language :: Python :: 3 :: Only
Classifier: Programming Language :: Python :: Implementation :: CPython
Requires-Python: >=3.11
License-File: LICENSE
Requires-Dist: mypy>=1.15.0
Requires-Dist: pyupgrade>=3.19.1
Requires-Dist: tokenize-rt>=6.1.0
Dynamic: license-file
